egaswahilicleaner
