Metadata-Version: 2.1
Name: egaswahilicleaner
Version: 0.0.7
Summary: Swahili text cleaning library
Home-page: 
Author: Shadrack Kajigili
Author-email: shadrackkajigili4@gmail.com
License: MIT
Keywords: swahili_text_cleaner
Classifier: Development Status :: 5 - Production/Stable
Classifier: Intended Audience :: Education
Classifier: Intended Audience :: Developers
Classifier: Operating System :: Microsoft :: Windows
Classifier: License :: OSI Approved :: MIT License
Classifier: Programming Language :: Python :: 3
Classifier: Operating System :: Unix
Classifier: Operating System :: iOS
License-File: LICENCE.txt
